{
    "boxShadow": "none",
    "mobileBottomRow": 4,
    "widgetName": "IconButton6",
    "buttonColor": "#1d4ed8",
    "displayName": "Icon button",
    "iconSVG": "/static/media/icon.b08054586989b185a0801e9a34f8ad49.svg",
    "searchTags": [
        "click",
        "submit"
    ],
    "topRow": 0,
    "bottomRow": 4,
    "parentRowSpace": 10,
    "type": "ICON_BUTTON_WIDGET",
    "hideCard": false,
    "mobileRightColumn": 63,
    "animateLoading": true,
    "parentColumnSpace": 15.59375,
    "dynamicTriggerPathList": [],
    "leftColumn": 57,
    "dynamicBindingPathList": [{"key": "borderRadius"}],
    "isDisabled": false,
    "key": "tsx1qt2gcx",
    "isDeprecated": false,
    "rightColumn": 61,
    "iconName": "print",
    "widgetId": "iqji362adv",
    "minWidth": 50,
    "isVisible": true,
    "version": 1,
    "parentId": "39h7uziz2l",
    "tags": ["Buttons"],
    "renderMode": "CANVAS",
    "isLoading": false,
    "mobileTopRow": 0,
    "responsiveBehavior": "hug",
    "borderRadius": "{{appsmith.theme.borderRadius.appBorderRadius}}",
    "mobileLeftColumn": 59,
    "buttonVariant": "PRIMARY"
}