{
    "boxShadow": "{{appsmith.theme.boxShadow.appBoxShadow}}",
    "borderColor": "#E0DEDE",
    "isVisibleDownload": true,
    "iconSVG": "/static/media/icon.e6911f8bb94dc6c4a102a74740c41763.svg",
    "topRow": 11,
    "isSortable": true,
    "type": "TABLE_WIDGET_V2",
    "inlineEditingSaveOption": "ROW_LEVEL",
    "animateLoading": true,
    "dynamicBindingPathList": [
        {"key": "accentColor"},
        {"key": "borderRadius"},
        {"key": "boxShadow"},
        {"key": "tableData"},
        {"key": "primaryColumns.ZHMC.computedValue"},
        {"key": "primaryColumns.ACTUAL_PRICE.computedValue"},
        {"key": "primaryColumns.DISCOUNT.computedValue"},
        {"key": "primaryColumns.STANDARD_PRICE.computedValue"},
        {"key": "primaryColumns.PAY_STATUS.computedValue"},
        {"key": "primaryColumns.PAY_MODE.computedValue"},
        {"key": "primaryColumns.ADD_FLAG.computedValue"},
        {"key": "primaryColumns.CHECK_DOCTOR.computedValue"},
        {"key": "primaryColumns.CHECK_STATUS.computedValue"},
        {"key": "primaryColumns.TCMC.computedValue"},
        {"key": "primaryColumns.DEPT_NAME.computedValue"},
        {"key": "primaryColumns.DEPARTMENT_ID.computedValue"},
        {"key": "primaryColumns.DEPT_ADDRESS.computedValue"},
        {"key": "primaryColumns.DEPT_REMARK.computedValue"},
        {"key": "primaryColumns.PHY_EXAM_TYPE.computedValue"},
        {"key": "primaryColumns.zhxmId.computedValue"}
    ],
    "needsHeightForContent": true,
    "leftColumn": 0,
    "delimiter": ",",
    "defaultSelectedRowIndex": 0,
    "accentColor": "{{appsmith.theme.colors.primaryColor}}",
    "isVisibleFilters": true,
    "isVisible": true,
    "enableClientSideSearch": true,
    "version": 2,
    "totalRecordsCount": 0,
    "tags": [
        "Suggested",
        "Display"
    ],
    "isLoading": false,
    "childStylesheet": {
        "button": {
            "boxShadow": "none",
            "borderRadius": "{{appsmith.theme.borderRadius.appBorderRadius}}",
            "buttonColor": "{{appsmith.theme.colors.primaryColor}}"
        },
        "iconButton": {
            "boxShadow": "none",
            "borderRadius": "{{appsmith.theme.borderRadius.appBorderRadius}}",
            "buttonColor": "{{appsmith.theme.colors.primaryColor}}"
        },
        "menuButton": {
            "boxShadow": "none",
            "borderRadius": "{{appsmith.theme.borderRadius.appBorderRadius}}",
            "menuColor": "{{appsmith.theme.colors.primaryColor}}"
        },
        "editActions": {
            "saveButtonColor": "{{appsmith.theme.colors.primaryColor}}",
            "saveBorderRadius": "{{appsmith.theme.borderRadius.appBorderRadius}}",
            "discardBorderRadius": "{{appsmith.theme.borderRadius.appBorderRadius}}",
            "discardButtonColor": "{{appsmith.theme.colors.primaryColor}}"
        }
    },
    "borderRadius": "{{appsmith.theme.borderRadius.appBorderRadius}}",
    "columnUpdatedAt": 1693534332627,
    "originalBottomRow": 40,
    "defaultSelectedRowIndices": [0],
    "mobileBottomRow": 39,
    "widgetName": "Table1",
    "defaultPageSize": 0,
    "columnOrder": [
        "ZHMC",
        "ACTUAL_PRICE",
        "DISCOUNT",
        "STANDARD_PRICE",
        "PAY_STATUS",
        "PAY_MODE",
        "ADD_FLAG",
        "CHECK_DOCTOR",
        "CHECK_STATUS",
        "TCMC",
        "DEPT_NAME",
        "DEPARTMENT_ID",
        "DEPT_ADDRESS",
        "DEPT_REMARK",
        "PHY_EXAM_TYPE",
        "zhxmId"
    ],
    "dynamicPropertyPathList": [],
    "displayName": "Table",
    "bottomRow": 39,
    "columnWidthMap": {},
    "parentRowSpace": 10,
    "hideCard": false,
    "mobileRightColumn": 34,
    "parentColumnSpace": 11.36865234375,
    "dynamicTriggerPathList": [],
    "borderWidth": "1",
    "primaryColumns": {
        "TCMC": {
            "computedValue": "{{Table1.processedTableData.map((currentRow, currentIndex) => ( currentRow[\"TCMC\"]))}}",
            "isEditable": false,
            "alias": "TCMC",
            "enableSort": true,
            "isSaveVisible": true,
            "id": "TCMC",
            "isDisabled": false,
            "allowSameOptionsInNewRow": true,
            "validation": {},
            "isCellVisible": true,
            "isDerived": false,
            "textSize": "0.875rem",
            "allowCellWrapping": false,
            "index": 10,
            "isDiscardVisible": true,
            "isVisible": true,
            "label": "TCMC",
            "columnType": "text",
            "horizontalAlignment": "LEFT",
            "isCellEditable": false,
            "width": 150,
            "enableFilter": true,
            "sticky": "",
            "originalId": "TCMC",
            "verticalAlignment": "CENTER"
        },
        "DEPT_NAME": {
            "computedValue": "{{Table1.processedTableData.map((currentRow, currentIndex) => ( currentRow[\"DEPT_NAME\"]))}}",
            "isEditable": false,
            "alias": "DEPT_NAME",
            "enableSort": true,
            "isSaveVisible": true,
            "id": "DEPT_NAME",
            "isDisabled": false,
            "allowSameOptionsInNewRow": true,
            "validation": {},
            "isCellVisible": true,
            "isDerived": false,
            "textSize": "0.875rem",
            "allowCellWrapping": false,
            "index": 11,
            "isDiscardVisible": true,
            "isVisible": true,
            "label": "DEPT_NAME",
            "columnType": "text",
            "horizontalAlignment": "LEFT",
            "isCellEditable": false,
            "width": 150,
            "enableFilter": true,
            "sticky": "",
            "originalId": "DEPT_NAME",
            "verticalAlignment": "CENTER"
        },
        "STANDARD_PRICE": {
            "computedValue": "{{Table1.processedTableData.map((currentRow, currentIndex) => ( currentRow[\"STANDARD_PRICE\"]))}}",
            "isEditable": false,
            "alias": "STANDARD_PRICE",
            "enableSort": true,
            "isSaveVisible": true,
            "id": "STANDARD_PRICE",
            "isDisabled": false,
            "allowSameOptionsInNewRow": true,
            "validation": {},
            "isCellVisible": true,
            "isDerived": false,
            "textSize": "0.875rem",
            "allowCellWrapping": false,
            "index": 4,
            "isDiscardVisible": true,
            "isVisible": true,
            "label": "STANDARD_PRICE",
            "columnType": "text",
            "horizontalAlignment": "LEFT",
            "isCellEditable": false,
            "width": 150,
            "enableFilter": true,
            "sticky": "",
            "originalId": "STANDARD_PRICE",
            "verticalAlignment": "CENTER"
        },
        "CHECK_STATUS": {
            "computedValue": "{{Table1.processedTableData.map((currentRow, currentIndex) => ( currentRow[\"CHECK_STATUS\"]))}}",
            "isEditable": false,
            "alias": "CHECK_STATUS",
            "enableSort": true,
            "isSaveVisible": true,
            "id": "CHECK_STATUS",
            "isDisabled": false,
            "allowSameOptionsInNewRow": true,
            "validation": {},
            "isCellVisible": true,
            "isDerived": false,
            "textSize": "0.875rem",
            "allowCellWrapping": false,
            "index": 9,
            "isDiscardVisible": true,
            "isVisible": true,
            "label": "CHECK_STATUS",
            "columnType": "text",
            "horizontalAlignment": "LEFT",
            "isCellEditable": false,
            "width": 150,
            "enableFilter": true,
            "sticky": "",
            "originalId": "CHECK_STATUS",
            "verticalAlignment": "CENTER"
        },
        "DEPARTMENT_ID": {
            "computedValue": "{{Table1.processedTableData.map((currentRow, currentIndex) => ( currentRow[\"DEPARTMENT_ID\"]))}}",
            "isEditable": false,
            "alias": "DEPARTMENT_ID",
            "enableSort": true,
            "isSaveVisible": true,
            "id": "DEPARTMENT_ID",
            "isDisabled": false,
            "allowSameOptionsInNewRow": true,
            "validation": {},
            "isCellVisible": true,
            "isDerived": false,
            "textSize": "0.875rem",
            "allowCellWrapping": false,
            "index": 12,
            "isDiscardVisible": true,
            "isVisible": true,
            "label": "DEPARTMENT_ID",
            "columnType": "text",
            "horizontalAlignment": "LEFT",
            "isCellEditable": false,
            "width": 150,
            "enableFilter": true,
            "sticky": "",
            "originalId": "DEPARTMENT_ID",
            "verticalAlignment": "CENTER"
        },
        "DEPT_REMARK": {
            "computedValue": "{{Table1.processedTableData.map((currentRow, currentIndex) => ( currentRow[\"DEPT_REMARK\"]))}}",
            "isEditable": false,
            "alias": "DEPT_REMARK",
            "enableSort": true,
            "isSaveVisible": true,
            "id": "DEPT_REMARK",
            "isDisabled": false,
            "allowSameOptionsInNewRow": true,
            "validation": {},
            "isCellVisible": true,
            "isDerived": false,
            "textSize": "0.875rem",
            "allowCellWrapping": false,
            "index": 14,
            "isDiscardVisible": true,
            "isVisible": true,
            "label": "DEPT_REMARK",
            "columnType": "text",
            "horizontalAlignment": "LEFT",
            "isCellEditable": false,
            "width": 150,
            "enableFilter": true,
            "sticky": "",
            "originalId": "DEPT_REMARK",
            "verticalAlignment": "CENTER"
        },
        "PAY_STATUS": {
            "computedValue": "{{Table1.processedTableData.map((currentRow, currentIndex) => ( currentRow[\"PAY_STATUS\"]))}}",
            "isEditable": false,
            "alias": "PAY_STATUS",
            "enableSort": true,
            "isSaveVisible": true,
            "id": "PAY_STATUS",
            "isDisabled": false,
            "allowSameOptionsInNewRow": true,
            "validation": {},
            "isCellVisible": true,
            "isDerived": false,
            "textSize": "0.875rem",
            "allowCellWrapping": false,
            "index": 5,
            "isDiscardVisible": true,
            "isVisible": true,
            "label": "PAY_STATUS",
            "columnType": "text",
            "horizontalAlignment": "LEFT",
            "isCellEditable": false,
            "width": 150,
            "enableFilter": true,
            "sticky": "",
            "originalId": "PAY_STATUS",
            "verticalAlignment": "CENTER"
        },
        "PAY_MODE": {
            "computedValue": "{{Table1.processedTableData.map((currentRow, currentIndex) => ( currentRow[\"PAY_MODE\"]))}}",
            "isEditable": false,
            "alias": "PAY_MODE",
            "enableSort": true,
            "isSaveVisible": true,
            "id": "PAY_MODE",
            "isDisabled": false,
            "allowSameOptionsInNewRow": true,
            "validation": {},
            "isCellVisible": true,
            "isDerived": false,
            "textSize": "0.875rem",
            "allowCellWrapping": false,
            "index": 6,
            "isDiscardVisible": true,
            "isVisible": true,
            "label": "PAY_MODE",
            "columnType": "text",
            "horizontalAlignment": "LEFT",
            "isCellEditable": false,
            "width": 150,
            "enableFilter": true,
            "sticky": "",
            "originalId": "PAY_MODE",
            "verticalAlignment": "CENTER"
        },
        "ZHMC": {
            "computedValue": "{{Table1.processedTableData.map((currentRow, currentIndex) => ( currentRow[\"ZHMC\"]))}}",
            "isEditable": false,
            "alias": "ZHMC",
            "enableSort": true,
            "isSaveVisible": true,
            "id": "ZHMC",
            "isDisabled": false,
            "allowSameOptionsInNewRow": true,
            "validation": {},
            "isCellVisible": true,
            "isDerived": false,
            "textSize": "0.875rem",
            "allowCellWrapping": false,
            "index": 0,
            "isDiscardVisible": true,
            "isVisible": true,
            "label": "ZHMC",
            "columnType": "text",
            "horizontalAlignment": "LEFT",
            "isCellEditable": false,
            "width": 150,
            "enableFilter": true,
            "sticky": "",
            "originalId": "ZHMC",
            "verticalAlignment": "CENTER"
        },
        "ACTUAL_PRICE": {
            "computedValue": "{{Table1.processedTableData.map((currentRow, currentIndex) => ( currentRow[\"ACTUAL_PRICE\"]))}}",
            "isEditable": false,
            "alias": "ACTUAL_PRICE",
            "enableSort": true,
            "isSaveVisible": true,
            "id": "ACTUAL_PRICE",
            "isDisabled": false,
            "allowSameOptionsInNewRow": true,
            "validation": {},
            "isCellVisible": true,
            "isDerived": false,
            "textSize": "0.875rem",
            "allowCellWrapping": false,
            "index": 2,
            "isDiscardVisible": true,
            "isVisible": true,
            "label": "ACTUAL_PRICE",
            "columnType": "text",
            "horizontalAlignment": "LEFT",
            "isCellEditable": false,
            "width": 150,
            "enableFilter": true,
            "sticky": "",
            "originalId": "ACTUAL_PRICE",
            "verticalAlignment": "CENTER"
        },
        "DISCOUNT": {
            "computedValue": "{{Table1.processedTableData.map((currentRow, currentIndex) => ( currentRow[\"DISCOUNT\"]))}}",
            "isEditable": false,
            "alias": "DISCOUNT",
            "enableSort": true,
            "isSaveVisible": true,
            "id": "DISCOUNT",
            "isDisabled": false,
            "allowSameOptionsInNewRow": true,
            "validation": {},
            "isCellVisible": true,
            "isDerived": false,
            "textSize": "0.875rem",
            "allowCellWrapping": false,
            "index": 3,
            "isDiscardVisible": true,
            "isVisible": true,
            "label": "DISCOUNT",
            "columnType": "text",
            "horizontalAlignment": "LEFT",
            "isCellEditable": false,
            "width": 150,
            "enableFilter": true,
            "sticky": "",
            "originalId": "DISCOUNT",
            "verticalAlignment": "CENTER"
        },
        "ADD_FLAG": {
            "computedValue": "{{Table1.processedTableData.map((currentRow, currentIndex) => ( currentRow[\"ADD_FLAG\"]))}}",
            "isEditable": false,
            "alias": "ADD_FLAG",
            "enableSort": true,
            "isSaveVisible": true,
            "id": "ADD_FLAG",
            "isDisabled": false,
            "allowSameOptionsInNewRow": true,
            "validation": {},
            "isCellVisible": true,
            "isDerived": false,
            "textSize": "0.875rem",
            "allowCellWrapping": false,
            "index": 7,
            "isDiscardVisible": true,
            "isVisible": true,
            "label": "ADD_FLAG",
            "columnType": "text",
            "horizontalAlignment": "LEFT",
            "isCellEditable": false,
            "width": 150,
            "enableFilter": true,
            "sticky": "",
            "originalId": "ADD_FLAG",
            "verticalAlignment": "CENTER"
        },
        "DEPT_ADDRESS": {
            "computedValue": "{{Table1.processedTableData.map((currentRow, currentIndex) => ( currentRow[\"DEPT_ADDRESS\"]))}}",
            "isEditable": false,
            "alias": "DEPT_ADDRESS",
            "enableSort": true,
            "isSaveVisible": true,
            "id": "DEPT_ADDRESS",
            "isDisabled": false,
            "allowSameOptionsInNewRow": true,
            "validation": {},
            "isCellVisible": true,
            "isDerived": false,
            "textSize": "0.875rem",
            "allowCellWrapping": false,
            "index": 13,
            "isDiscardVisible": true,
            "isVisible": true,
            "label": "DEPT_ADDRESS",
            "columnType": "text",
            "horizontalAlignment": "LEFT",
            "isCellEditable": false,
            "width": 150,
            "enableFilter": true,
            "sticky": "",
            "originalId": "DEPT_ADDRESS",
            "verticalAlignment": "CENTER"
        },
        "CHECK_DOCTOR": {
            "computedValue": "{{Table1.processedTableData.map((currentRow, currentIndex) => ( currentRow[\"CHECK_DOCTOR\"]))}}",
            "isEditable": false,
            "alias": "CHECK_DOCTOR",
            "enableSort": true,
            "isSaveVisible": true,
            "id": "CHECK_DOCTOR",
            "isDisabled": false,
            "allowSameOptionsInNewRow": true,
            "validation": {},
            "isCellVisible": true,
            "isDerived": false,
            "textSize": "0.875rem",
            "allowCellWrapping": false,
            "index": 8,
            "isDiscardVisible": true,
            "isVisible": true,
            "label": "CHECK_DOCTOR",
            "columnType": "text",
            "horizontalAlignment": "LEFT",
            "isCellEditable": false,
            "width": 150,
            "enableFilter": true,
            "sticky": "",
            "originalId": "CHECK_DOCTOR",
            "verticalAlignment": "CENTER"
        },
        "PHY_EXAM_TYPE": {
            "computedValue": "{{Table1.processedTableData.map((currentRow, currentIndex) => ( currentRow[\"PHY_EXAM_TYPE\"]))}}",
            "isEditable": false,
            "alias": "PHY_EXAM_TYPE",
            "enableSort": true,
            "isSaveVisible": true,
            "id": "PHY_EXAM_TYPE",
            "isDisabled": false,
            "allowSameOptionsInNewRow": true,
            "validation": {},
            "isCellVisible": true,
            "isDerived": false,
            "textSize": "0.875rem",
            "allowCellWrapping": false,
            "index": 15,
            "isDiscardVisible": true,
            "isVisible": true,
            "label": "PHY_EXAM_TYPE",
            "columnType": "text",
            "horizontalAlignment": "LEFT",
            "isCellEditable": false,
            "width": 150,
            "enableFilter": true,
            "sticky": "",
            "originalId": "PHY_EXAM_TYPE",
            "verticalAlignment": "CENTER"
        },
        "zhxmId": {
            "computedValue": "{{Table1.processedTableData.map((currentRow, currentIndex) => ( currentRow[\"zhxmId\"]))}}",
            "isEditable": false,
            "alias": "zhxmId",
            "enableSort": true,
            "isSaveVisible": true,
            "id": "zhxmId",
            "isDisabled": false,
            "allowSameOptionsInNewRow": true,
            "validation": {},
            "isCellVisible": true,
            "isDerived": false,
            "textSize": "0.875rem",
            "allowCellWrapping": false,
            "index": 1,
            "isDiscardVisible": true,
            "isVisible": true,
            "label": "zhxmId",
            "fontStyle": "",
            "textColor": "",
            "columnType": "text",
            "horizontalAlignment": "LEFT",
            "isCellEditable": false,
            "width": 150,
            "enableFilter": true,
            "sticky": "",
            "originalId": "zhxmId",
            "cellBackground": "",
            "verticalAlignment": "CENTER"
        }
    },
    "key": "jqs4jz6mg0",
    "canFreezeColumn": true,
    "isDeprecated": false,
    "rightColumn": 64,
    "textSize": "0.875rem",
    "widgetId": "eilsuerg6u",
    "minWidth": 450,
    "tableData": "{{tjxm.data}}",
    "label": "Data",
    "searchKey": "",
    "parentId": "4ea1zijaka",
    "renderMode": "CANVAS",
    "mobileTopRow": 11,
    "horizontalAlignment": "LEFT",
    "isVisibleSearch": true,
    "responsiveBehavior": "fill",
    "originalTopRow": 12,
    "mobileLeftColumn": 0,
    "isVisiblePagination": true,
    "verticalAlignment": "CENTER"
}